lins_dbfields/__init__.py
lins_dbfields/default.py
lins_dbfields/raw.py
lins_dbfields-0.4.0.13.dist-info/METADATA
lins_dbfields-0.4.0.13.dist-info/WHEEL
lins_dbfields-0.4.0.13.dist-info/top_level.txt
lins_dbfields-0.4.0.13.dist-info/RECORD
