Metadata-Version: 2.1
Name: lins-dbfields
Version: 0.4.0.13
Summary: Classes de fields customizados para o Django.
Home-page: https://bitbucket.org/grupolinsferrao/pypck-lins_dbfields/
Author: Lucas Lehnen
Author-email: lucas@lojaspompeia.com.br
License: MIT
Platform: UNKNOWN
